podtuber/__init__.py
podtuber/main.py
podtuber/utils.py
podtuber/youtube_parser.py
podtuber-0.1.1.dist-info/entry_points.txt
podtuber-0.1.1.dist-info/WHEEL
podtuber-0.1.1.dist-info/METADATA
podtuber-0.1.1.dist-info/RECORD
