Metadata-Version: 2.1
Name: podtuber
Version: 0.1.1
Summary: Simple Python application to create podcast `.rss` files from YouTube playlists.
Home-page: https://github.com/ZvikaZ/podtuber
Author: Zvika Haramaty
Author-email: haramaty.zvika@gmail.com
Requires-Python: >=3.10,<4.0
Classifier: Programming Language :: Python :: 3
Classifier: Programming Language :: Python :: 3.10
Classifier: Programming Language :: Python :: 3.11
Requires-Dist: pathvalidate (>=3.1.0,<4.0.0)
Requires-Dist: podgen (>=1.1.0,<2.0.0)
Requires-Dist: pytube (>=15.0.0,<16.0.0)
Requires-Dist: tomli (>=2.0.1,<3.0.0)
Project-URL: Repository, https://github.com/ZvikaZ/podtuber
